[
    {
        "index": "1",
        "state": "Andaman and Nicobar Islands",
        "cases": "33",
        "recovered": "33",
        "dead": "0"
    },
    {
        "index": "2",
        "state": "Andhra Pradesh",
        "cases": "2090",
        "recovered": "1056",
        "dead": "46"
    },
    {
        "index": "3",
        "state": "Arunachal Pradesh",
        "cases": "1",
        "recovered": "1",
        "dead": "0"
    },
    {
        "index": "4",
        "state": "Assam",
        "cases": "65",
        "recovered": "39",
        "dead": "2"
    },
    {
        "index": "5",
        "state": "Bihar",
        "cases": "831",
        "recovered": "383",
        "dead": "6"
    },
    {
        "index": "6",
        "state": "Chandigarh",
        "cases": "187",
        "recovered": "28",
        "dead": "3"
    },
    {
        "index": "7",
        "state": "Chhattisgarh",
        "cases": "59",
        "recovered": "54",
        "dead": "0"
    },
    {
        "index": "8",
        "state": "Dadar Nagar Haveli",
        "cases": "1",
        "recovered": "0",
        "dead": "0"
    },
    {
        "index": "9",
        "state": "Delhi",
        "cases": "7639",
        "recovered": "2512",
        "dead": "86"
    },
    {
        "index": "10",
        "state": "Goa",
        "cases": "7",
        "recovered": "7",
        "dead": "0"
    },
    {
        "index": "11",
        "state": "Gujarat",
        "cases": "8903",
        "recovered": "3246",
        "dead": "537"
    },
    {
        "index": "12",
        "state": "Haryana",
        "cases": "780",
        "recovered": "342",
        "dead": "11"
    },
    {
        "index": "13",
        "state": "Himachal Pradesh",
        "cases": "65",
        "recovered": "39",
        "dead": "2"
    },
    {
        "index": "14",
        "state": "Jammu and Kashmir",
        "cases": "934",
        "recovered": "455",
        "dead": "10"
    },
    {
        "index": "15",
        "state": "Jharkhand",
        "cases": "172",
        "recovered": "79",
        "dead": "3"
    },
    {
        "index": "16",
        "state": "Karnataka",
        "cases": "925",
        "recovered": "433",
        "dead": "31"
    },
    {
        "index": "17",
        "state": "Kerala",
        "cases": "524",
        "recovered": "489",
        "dead": "4"
    },
    {
        "index": "18",
        "state": "Ladakh",
        "cases": "42",
        "recovered": "21",
        "dead": "0"
    },
    {
        "index": "19",
        "state": "Madhya Pradesh",
        "cases": "3986",
        "recovered": "1860",
        "dead": "225"
    },
    {
        "index": "20",
        "state": "Maharashtra",
        "cases": "24427",
        "recovered": "5125",
        "dead": "921"
    },
    {
        "index": "21",
        "state": "Manipur",
        "cases": "2",
        "recovered": "2",
        "dead": "0"
    },
    {
        "index": "22",
        "state": "Meghalaya",
        "cases": "13",
        "recovered": "10",
        "dead": "1"
    },
    {
        "index": "23",
        "state": "Mizoram",
        "cases": "1",
        "recovered": "1",
        "dead": "0"
    },
    {
        "index": "24",
        "state": "Odisha",
        "cases": "437",
        "recovered": "116",
        "dead": "3"
    },
    {
        "index": "25",
        "state": "Puducherry",
        "cases": "13",
        "recovered": "9",
        "dead": "1"
    },
    {
        "index": "26",
        "state": "Punjab",
        "cases": "1914",
        "recovered": "171",
        "dead": "32"
    },
    {
        "index": "27",
        "state": "Rajasthan",
        "cases": "4126",
        "recovered": "2378",
        "dead": "117"
    },
    {
        "index": "28",
        "state": "Tamil Nadu",
        "cases": "8718",
        "recovered": "2134",
        "dead": "61"
    },
    {
        "index": "29",
        "state": "Telengana",
        "cases": "1326",
        "recovered": "830",
        "dead": "32"
    },
    {
        "index": "30",
        "state": "Tripura",
        "cases": "154",
        "recovered": "2",
        "dead": "0"
    },
    {
        "index": "31",
        "state": "Uttarakhand",
        "cases": "69",
        "recovered": "46",
        "dead": "1"
    },
    {
        "index": "32",
        "state": "Uttar Pradesh",
        "cases": "3664",
        "recovered": "1873",
        "dead": "82"
    }
]